preprocessing/__init__.py
preprocessing/agglomerative_clustering.py
preprocessing/cli.py
preprocessing/dimensionality_reduction.py
preprocessing/embedding_service.py
preprocessing/visualization_service.py
embedprepro-0.22.dist-info/METADATA
embedprepro-0.22.dist-info/WHEEL
embedprepro-0.22.dist-info/entry_points.txt
embedprepro-0.22.dist-info/top_level.txt
embedprepro-0.22.dist-info/RECORD
