Metadata-Version: 2.1
Name: embedprepro
Version: 0.22
Home-page: https://github.com/Elma-dev/embedprepro-lib.git/
Author-email: elmajjodi.abdeljalil@gmail.com
Requires-Dist: click (==8.1.7)
Requires-Dist: matplotlib (==3.9.0)
Requires-Dist: numpy (==1.26.4)
Requires-Dist: pandas (==2.2.2)
Requires-Dist: seaborn (==0.13.2)
Requires-Dist: sentence-transformers (==2.7.0)
Requires-Dist: setuptools (==65.6.3)
Requires-Dist: tqdm (==4.66.4)
Requires-Dist: umap-learn (==0.5.6)
